src/__init__.py
src/main.py
src/config/__init__.py
src/config/config.py
src/model/__init__.py
src/model/pipeline.py
src/model/predict.py
src/model/train_pipeline.py
src/preprocessing/__init__.py
src/preprocessing/datamanager.py
src/test/__init__.py
src/test/test_bound_outliers.py
src/test/test_load_from_database.py
src/test/test_pipline.py
src/test/test_predict.py
src/test/test_preprocess_data.py
src/test/test_preprocess_input.py
aiap_model-0.0.0.dist-info/METADATA
aiap_model-0.0.0.dist-info/WHEEL
aiap_model-0.0.0.dist-info/top_level.txt
aiap_model-0.0.0.dist-info/RECORD
