Metadata-Version: 2.1
Name: aiap-model
Version: 0.0.0
Summary: Example classification model package from AIAP assessment.
Home-page: https://github.com/ChngYuanLongRandy/AIAP
Author: Randy Chng
Author-email: chngyuanlong@gmail.com
License: BSD-3
Platform: UNKNOWN
Classifier: License :: OSI Approved :: MIT License
Classifier: Programming Language :: Python :: 3.10
Classifier: Programming Language :: Python :: Implementation :: CPython
Classifier: Programming Language :: Python :: Implementation :: PyPy
Requires-Python: ==3.10.0
Requires-Dist: numpy (==1.22.0)
Requires-Dist: pandas (==1.3.5)
Requires-Dist: sklearn (==0.0)
Requires-Dist: tox (==3.24.5)
Requires-Dist: virtualenv (==20.13.0)
Requires-Dist: streamlit (==1.3.1)
